{
  "questions": [
    {
      "question": "What is Angular primarily used for?",
      "options": [
        "Backend development",
        "Building single-page web applications",
        "Game development",
        "Database management"
      ],
      "answer": 1,
      "explanation": "Angular is mainly used to build single-page applications (SPAs)."
    },
    {
      "question": "Which language is primarily used to write Angular applications?",
      "options": [
        "Java",
        "JavaScript",
        "TypeScript",
        "Dart"
      ],
      "answer": 2,
      "explanation": "Angular is built with TypeScript, which is a superset of JavaScript."
    }
  ],
  "attempts": [
    {
      "id": "15ef",
      "moduleId": 1,
      "score": 2,
      "total": 2,
      "duration": 3,
      "timestamp": 1744334923884,
      "answers": [
        {
          "question": "What is Angular primarily used for?",
          "selectedOption": 1,
          "correctOption": 1,
          "isCorrect": true
        },
        {
          "question": "Which language is primarily used to write Angular applications?",
          "selectedOption": 2,
          "correctOption": 2,
          "isCorrect": true
        }
      ]
    },
    {
      "id": "9596",
      "moduleId": 1,
      "score": 2,
      "total": 2,
      "duration": 3,
      "timestamp": 1744335155194,
      "answers": [
        {
          "question": "What is Angular primarily used for?",
          "selectedOption": 1,
          "correctOption": 1,
          "isCorrect": true
        },
        {
          "question": "Which language is primarily used to write Angular applications?",
          "selectedOption": 2,
          "correctOption": 2,
          "isCorrect": true
        }
      ]
    }
  ]
}